pykrete
