Metadata-Version: 2.1
Name: pykrete
Version: 1.4.7
Summary: Build script foundation
Home-page: http://ait-tool-center.iil.intel.com/
Author: Shai A. Bennathan
Author-email: shai.bennathan@intel.com
License: MIT
Platform: UNKNOWN
Classifier: Development Status :: 5 - Production/Stable
Classifier: Intended Audience :: Developers
Classifier: Programming Language :: Python :: 3.6
Classifier: License :: OSI Approved :: MIT License
Classifier: Operating System :: OS Independent
Requires-Python: >=3.6
